gmail_smtplib_micro/__init__.py
gmail_smtplib_micro/_email.py
gmail_smtplib_micro/_examples.py
gmail_smtplib_micro/_exceptions.py
gmail_smtplib_micro/_utils.py
gmail_smtplib_micro/gmail_smtplib_micro.py
gmail_smtplib_micro-0.1.2.dist-info/METADATA
gmail_smtplib_micro-0.1.2.dist-info/WHEEL
gmail_smtplib_micro-0.1.2.dist-info/licenses/LICENSE
gmail_smtplib_micro-0.1.2.dist-info/RECORD
