Metadata-Version: 2.3
Name: gmail_smtplib_micro
Version: 0.1.2
Summary: A wrapper for sending emails via gmail
Author: Samuel Shiels
License-File: LICENSE
Classifier: Development Status :: 3 - Alpha
Classifier: Environment :: Other Environment
Classifier: Intended Audience :: Developers
Classifier: Intended Audience :: System Administrators
Classifier: License :: OSI Approved :: MIT License
Classifier: Operating System :: POSIX :: Linux
Classifier: Programming Language :: Python :: 3
Classifier: Topic :: Utilities
Requires-Python: >=3.11.5
